Workbook

Sheet README
B2: Tata Motors — Business Stress Testing & Survival Simulator
B3: A driver-based financial model to test how Tata Motors' profitability, cash flow and debt position would hold up under adverse business conditions.
B5: Purpose
B6: Answers: 'How much financial stress can Tata Motors withstand before profitability or cash flow is seriously affected?' Not a forecast — a scenario stress-test.
B8: How it works
B9: Historicals (FY22-FY25) → Assumptions (scenario drivers, edit the YELLOW cells) → Scenario Model (projects next year under 4 cases) → Dashboard (compares outcomes).
B11: Scenarios
B12: Base Case (steady state) | Optimistic Case (demand tailwinds) | Stress Case (moderate shock) | Extreme Stress Case (severe, compounding shock).
B14: Sheets
B15: 1. Historicals 2. Segment Data 3. Assumptions 4. Scenario Model 5. Dashboard
B17: Colour key
B18: Blue text = hardcoded input/actual. Black text = formula. Green text = link to another sheet. Yellow fill = assumption you should edit to run your own scenarios.
... B24: FY24 figures are restated in the FY25 report following the Tata Motors Finance Ltd - Tata Capital merger (discontinued operations). Historicals sheet uses each year's originally reported figures; FY25 total PAT includes ₹4,871 cr from discontinued operations, shown separately.

Sheet Historicals
A1: Tata Motors — Consolidated Historical Financials (₹ crores)
A2: Source: Consolidated Financial Statements, Integrated Annual Reports FY2022-23, FY2023-24, FY2024-25 (tatamotors.com)
A4: Particulars | B4: FY22 | C4: FY23 | D4: FY24 | E4: FY25
A5: Revenue from operations | B5: 278453.62 | C5: 345966.97 | D5: 437927.77 | E5: 439695
A6: Cost of materials consumed (incl. hedge adj.) | B6: 160920.56 | C6: 208944.31 | D6: 249277.79 | E6: 241148
A7: Purchase of products for sale | B7: 18374.77 | C7: 22306.95 | D7: 25043.44 | E7: 27802
A8: Changes in inventories | B8: 1590.49 | C8: -4781.62 | D8: -1565.53 | E8: 2836
A9: Employee benefits expense | B9: 30808.52 | C9: 33654.7 | D9: 42486.64 | E9: 47767
A10: Other expenses | B10: 47133.85 | C10: 61785.96 | D10: 78874.98 | E10: 85399
A11: Product development / engineering expenses | B11: 9209.5 | C11: 10661.96 | D11: 10958.72 | E11: 10716
A12: EBITDA | B12: =B5-B6-B7-B8-B9-B10-B11-B20 -> 24813.22 | C12: =C5-C6-C7-C8-C9-C10-C11-C20 -> 31829.55 | D12: =D5-D6-D7-D8-D9-D10-D11-D20 -> 59610.08 | E12: =E5-E6-E7-E8-E9-E10-E11-E20 -> 55132
A13: Depreciation & amortisation expense | B13: 24835.69 | C13: 24860.36 | D13: 27270.13 | E13: 23256
A14: EBIT | B14: =B12-B13 -> -22.47 | C14: =C12-C13 -> 6969.19 | D14: =D12-D13 -> 32339.95 | E14: =E12-E13 -> 31876
A15: Finance costs | B15: 9311.86 | C15: 10225.48 | D15: 9985.76 | E15: 5083
A16: Profit before tax (model, ex. FX/other one-offs) | B16: =B14-B15 -> -9334.33 | C16: =C14-C15 -> -3256.29 | D16: =D14-D15 -> 22354.19 | E16: =E14-E15 -> 26793
A17: Tax expense | B17: 4231.29 | C17: 704.06 | D17: -3851.64 | E17: 10502
A18: Profit after tax (model, ex. FX/other one-offs) | B18: =B16-B17 -> -13565.62 | C18: =C16-C17 -> -3960.35 | D18: =D16-D17 -> 26205.83 | E18: =E16-E17 -> 16291
A19: Reported Profit for the year (per Annual Report) | B19: -11308.76 | C19: 2689.87 | D19: 31806.75 | E19: 28149
A20: Less: Amount transferred to capital and other account (capitalised R&D/development costs, credit) | B20: -14397.29 | C20: -18434.84 | D20: -26758.35 | E20: -31105
A21: Debt, Assets & Cash Flow
A22: Total Borrowings (non-current + current) | B22: 139677.04 | C22: 125660.47 | D22: 98500.09 | E22: 62499
A23: Total Assets | B23: 330619.93 | C23: 336081.38 | D23: 370663.96 | E23: 378642
A24: Net Cash from Operating Activities | B24: 14282.83 | C24: 35388.01 | D24: 67915.36 | E24: 63102
A25: Capex (PP&E + intangible assets) | B25: 15168.42 | C25: 18095.68 | D25: 31413.63 | E25: 38042
A26: Free Cash Flow | B26: =B24-B25 -> -885.59 | C26: =C24-C25 -> 17292.33 | D26: =D24-D25 -> 36501.73 | E26: =E24-E25 -> 25060
A27: Implied Interest Rate on Debt | B27: =B15/B22 -> 0.066667077 | C27: =C15/C22 -> 0.08137388 | D27: =D15/D22 -> 0.10137818 | E27: =E15/E22 -> 0.081329301
A28: EBITDA Margin | B28: =B12/B5 -> 0.089110783 | C28: =C12/C5 -> 0.092001702 | D28: =D12/D5 -> 0.13611852 | E28: =E12/E5 -> 0.12538692
A29: Net Debt / EBITDA | B29: =B22/B12 -> 5.629138 | C29: =C22/C12 -> 3.9479185 | D29: =D22/D12 -> 1.6524066 | E29: =E22/E12 -> 1.1336248
A31: Note: 'Cost of materials consumed' includes basis adjustment on hedge-accounted derivatives for FY22/FY23 to match the FY24 report's presentation. All figures as reported in each year's Consolidated Statement of Profit & Loss / Balance Sheet / Cash Flow Statement.

Sheet Segment Data
A1: Tata Motors — Segment Revenue & Results (₹ crores)
A2: Source: Note 45 'Segment Reporting', Consolidated Financial Statements, FY2022-23 / FY2023-24 / FY2024-25 Annual Reports
A4: Particulars | B4: FY23 | C4: FY24 | D4: FY25
A5: Tata Commercial Vehicles (CV)
A6: External Revenue | B6: 69324.4 | C6: 76961.19 | D6: 74049
A7: Segment Result (EBIT) | B7: 3693.28 | C7: 6483.46 | D7: 6814
A8: Tata Passenger Vehicles incl. EV (PV)
A9: External Revenue | B9: 45845.17 | C9: 50278.22 | D9: 47807
A10: Segment Result (EBIT) | B10: 542.17 | C10: 1015.8 | D10: 472
A11: Jaguar Land Rover (JLR)
A12: External Revenue | B12: 222845.42 | C12: 302755.82 | D12: 314032
A13: Segment Result (EBIT) | B13: 3481.69 | C13: 25381.9 | D13: 27764
A14: Vehicle Financing & Others
A15: External Revenue (Vehicle Financing + 'Others' segment) | B15: 7764.57 | C15: 7919.12 | D15: 3792
A16: Segment Result (EBIT) | B16: -558.85 | C16: 71.05 | D16: 669
A18: Total External Revenue (check) | B18: =B6+B9+B12+B15 -> 345779.56 | C18: =C6+C9+C12+C15 -> 437914.35 | D18: =D6+D9+D12+D15 -> 439680
A20: Note: 'Vehicle Financing & Others' combines the Vehicle Financing sub-segment with the 'Others' segment (IT services & insurance broking) since neither is individually material. Row 18 should reconcile closely to 'Revenue from operations' on the Historicals sheet (small gaps are intra-segment eliminations).

Sheet Assumptions
A1: Scenario Assumptions — FY26 Stress-Test Drivers
A2: Edit the YELLOW cells to define your own scenarios. All other sheets recalculate automatically.
A4: Driver | B4: Base Case | C4: Optimistic Case | D4: Stress Case | E4: Extreme Stress Case
A5: Volume / Demand Drivers
A6: CV Volume Growth % | B6: 0.05 | C6: 0.12 | D6: -0.1 | E6: -0.2
A7: PV/EV Volume Growth % | B7: 0.05 | C7: 0.12 | D7: -0.1 | E7: -0.2
A8: JLR Volume Growth % | B8: 0.05 | C8: 0.1 | D8: -0.15 | E8: -0.25
A9: Vehicle Financing & Others Revenue Growth % | B9: 0.05 | C9: 0.08 | D9: -0.05 | E9: -0.15
A10: Pricing
A11: Blended Selling Price Change % (all segments) | B11: 0 | C11: 0.02 | D11: -0.02 | E11: -0.05
A12: Cost Drivers
A13: Material Cost (% of Revenue) | B13: 0.548 | C13: 0.538 | D13: 0.568 | E13: 0.598
A14: Employee Cost Growth % | B14: 0.08 | C14: 0.08 | D14: 0.06 | E14: 0.03
A15: Other Operating Expense Growth % | B15: 0.08 | C15: 0.08 | D15: 0.06 | E15: 0.03
A16: D&A Growth % | B16: 0.02 | C16: 0.02 | D16: 0 | E16: -0.02
A17: Financing & Tax
A18: Interest Rate on Borrowings % | B18: 0.081 | C18: 0.081 | D18: 0.095 | E18: 0.11
A19: Corporate Tax Rate % | B19: 0.25 | C19: 0.25 | D19: 0.25 | E19: 0.25
A20: Capex Growth % | B20: 0.05 | C20: 0.1 | D20: -0.1 | E20: -0.25
A21: Capitalisation Rate (% of Revenue) — R&D/development costs capitalised | B21: 0.07 | C21: 0.075 | D21: 0.05 | E21: 0.03
A22: Row reference (for the Scenario Model formulas): CV growth=6, PV growth=7, JLR growth=8, VF&Others growth=9, Price change=11, Material cost %=13, Employee growth=14, Other opex growth=15, D&A growth=16, Interest rate=18, Tax rate=19, Capex growth=20.

Sheet Scenario Model
A1: FY26 Scenario Model — Base / Optimistic / Stress / Extreme Stress
A2: All figures ₹ crores unless noted. Formulas project FY26 off FY25 actuals (Historicals, Segment Data) using the Assumptions sheet drivers.
A4: Line Item | B4: Base Case | C4: Optimistic Case | D4: Stress Case | E4: Extreme Stress Case
A5: Revenue Build (Segment Data FY25 base x Assumptions growth x price change)
A6: CV Revenue | B6: ='Segment Data'!$D6*(1+Assumptions!B6)*(1+Assumptions!B11) -> 77751.45 | C6: ='Segment Data'!$D6*(1+Assumptions!C6)*(1+Assumptions!C11) -> 84593.578 | D6: ='Segment Data'!$D6*(1+Assumptions!D6)*(1+Assumptions!D11) -> 65311.218 | E6: ='Segment Data'!$D6*(1+Assumptions!E6)*(1+Assumptions!E11) -> 56277.24
A7: PV/EV Revenue | B7: ='Segment Data'!$D9*(1+Assumptions!B7)*(1+Assumptions!B11) -> 50197.35 | C7: ='Segment Data'!$D9*(1+Assumptions!C7)*(1+Assumptions!C11) -> 54614.717 | D7: ='Segment Data'!$D9*(1+Assumptions!D7)*(1+Assumptions!D11) -> 42165.774 | E7: ='Segment Data'!$D9*(1+Assumptions!E7)*(1+Assumptions!E11) -> 36333.32
A8: JLR Revenue | B8: ='Segment Data'!$D12*(1+Assumptions!B8)*(1+Assumptions!B11) -> 329733.6 | C8: ='Segment Data'!$D12*(1+Assumptions!C8)*(1+Assumptions!C11) -> 352343.9 | D8: ='Segment Data'!$D12*(1+Assumptions!D8)*(1+Assumptions!D11) -> 261588.66 | E8: ='Segment Data'!$D12*(1+Assumptions!E8)*(1+Assumptions!E11) -> 223747.8
A9: Vehicle Financing & Others Revenue | B9: ='Segment Data'!$D15*(1+Assumptions!B9) -> 3981.6 | C9: ='Segment Data'!$D15*(1+Assumptions!C9) -> 4095.36 | D9: ='Segment Data'!$D15*(1+Assumptions!D9) -> 3602.4 | E9: ='Segment Data'!$D15*(1+Assumptions!E9) -> 3223.2
A10: Total Revenue | B10: =SUM(B6:B9) -> 461664 | C10: =SUM(C6:C9) -> 495647.56 | D10: =SUM(D6:D9) -> 372668.05 | E10: =SUM(E6:E9) -> 319581.56
A12: Costs
A13: Material Costs (Revenue x Material Cost %) | B13: =B10*Assumptions!B13 -> 252991.87 | C13: =C10*Assumptions!C13 -> 266658.39 | D13: =D10*Assumptions!D13 -> 211675.45 | E13: =E10*Assumptions!E13 -> 191109.77
A14: Employee Costs | B14: =Historicals!$E$9*(1+Assumptions!B14) -> 51588.36 | C14: =Historicals!$E$9*(1+Assumptions!C14) -> 51588.36 | D14: =Historicals!$E$9*(1+Assumptions!D14) -> 50633.02 | E14: =Historicals!$E$9*(1+Assumptions!E14) -> 49200.01
A15: Other Operating Expenses, net of capitalised R&D/dev. costs (Assumptions row 21) | B15: =(Historicals!$E$7+Historicals!$E$8+Historicals!$E$10+Historicals!$E$11)*(1+Assumptions!B15)-B10*Assumptions!B21 -> 104576.76 | C15: =(Historicals!$E$7+Historicals!$E$8+Historicals!$E$10+Historicals!$E$11)*(1+Assumptions!C15)-C10*Assumptions!C21 -> 99719.673 | D15: =(Historicals!$E$7+Historicals!$E$8+Historicals!$E$10+Historicals!$E$11)*(1+Assumptions!D15)-D10*Assumptions!D21 -> 115724.78 | E15: =(Historicals!$E$7+Historicals!$E$8+Historicals!$E$10+Historicals!$E$11)*(1+Assumptions!E15)-E10*Assumptions!E21 -> 120968.14
A16: EBITDA | B16: =B10-B13-B14-B15 -> 52507.008 | C16: =C10-C13-C14-C15 -> 77681.139 | D16: =D10-D13-D14-D15 -> -5365.2009 | E16: =E10-E13-E14-E15 -> -41696.366
A17: EBITDA Margin % | B17: =B16/B10 -> 0.11373425 | C17: =C16/C10 -> 0.15672656 | D17: =D16/D10 -> -0.014396729 | E17: =E16/E10 -> -0.13047175
A19: Profitability
A20: Depreciation & Amortisation | B20: =Historicals!$E$13*(1+Assumptions!B16) -> 23721.12 | C20: =Historicals!$E$13*(1+Assumptions!C16) -> 23721.12 | D20: =Historicals!$E$13*(1+Assumptions!D16) -> 23256 | E20: =Historicals!$E$13*(1+Assumptions!E16) -> 22790.88
A21: EBIT | B21: =B16-B20 -> 28785.888 | C21: =C16-C20 -> 53960.019 | D21: =D16-D20 -> -28621.201 | E21: =E16-E20 -> -64487.246
A22: Total Debt (held at FY25 level) | B22: =Historicals!$E$22 -> 62499 | C22: =Historicals!$E$22 -> 62499 | D22: =Historicals!$E$22 -> 62499 | E22: =Historicals!$E$22 -> 62499
A23: Interest Expense | B23: =B22*Assumptions!B18 -> 5062.419 | C23: =C22*Assumptions!C18 -> 5062.419 | D23: =D22*Assumptions!D18 -> 5937.405 | E23: =E22*Assumptions!E18 -> 6874.89
A24: Profit Before Tax | B24: =B21-B23 -> 23723.469 | C24: =C21-C23 -> 48897.6 | D24: =D21-D23 -> -34558.606 | E24: =E21-E23 -> -71362.136
A25: Tax Expense | B25: =MAX(B24,0)*Assumptions!B19 -> 5930.8672 | C25: =MAX(C24,0)*Assumptions!C19 -> 12224.4 | D25: =MAX(D24,0)*Assumptions!D19 -> 0 | E25: =MAX(E24,0)*Assumptions!E19 -> 0
A26: Net Profit (PAT) | B26: =B24-B25 -> 17792.602 | C26: =C24-C25 -> 36673.2 | D26: =D24-D25 -> -34558.606 | E26: =E24-E25 -> -71362.136
A27: Net Profit Margin % | B27: =B26/B10 -> 0.038540154 | C27: =C26/C10 -> 0.073990478 | D27: =D26/D10 -> -0.092732946 | E27: =E26/E10 -> -0.22329867
A28: Interest Coverage Ratio (EBIT / Interest) | B28: =B21/B23 -> 5.6861923 | C28: =C21/C23 -> 10.65894 | D28: =D21/D23 -> -4.8204899 | E28: =E21/E23 -> -9.3801131
A30: Cash Flow & Balance Sheet Stress
A31: Operating Cash Flow (proxy: PAT + D&A) | B31: =B26+B20 -> 41513.722 | C31: =C26+C20 -> 60394.32 | D31: =D26+D20 -> -11302.606 | E31: =E26+E20 -> -48571.256
A32: Capex | B32: =Historicals!$E$25*(1+Assumptions!B20) -> 39944.1 | C32: =Historicals!$E$25*(1+Assumptions!C20) -> 41846.2 | D32: =Historicals!$E$25*(1+Assumptions!D20) -> 34237.8 | E32: =Historicals!$E$25*(1+Assumptions!E20) -> 28531.5
A33: Free Cash Flow | B33: =B31-B32 -> 1569.6217 | C33: =C31-C32 -> 18548.12 | D33: =D31-D32 -> -45540.406 | E33: =E31-E32 -> -77102.756
A34: Net Debt / EBITDA | B34: =B22/B16 -> 1.1902983 | C34: =C22/C16 -> 0.80455824 | D34: =D22/D16 -> -11.648958 | E34: =E22/E16 -> -1.4989076
A36: Row map for Dashboard sheet -> Revenue:10, EBITDA:16, EBITDA Margin:17, EBIT:21, PBT:24, PAT:26, Net Margin:27, Interest Coverage:28, Op Cash Flow:31, Capex:32, Free Cash Flow:33, Net Debt/EBITDA:34

Sheet Dashboard
A1: Tata Motors — Stress Test Dashboard (FY26 Scenarios)
A2: How much financial stress can Tata Motors withstand before profitability or cash flow is seriously affected?
A4: Metric | B4: Base Case | C4: Optimistic Case | D4: Stress Case | E4: Extreme Stress Case
A5: Total Revenue (₹ cr) | B5: ='Scenario Model'!B10 -> 461664 | C5: ='Scenario Model'!C10 -> 495647.56 | D5: ='Scenario Model'!D10 -> 372668.05 | E5: ='Scenario Model'!E10 -> 319581.56
A6: EBITDA (₹ cr) | B6: ='Scenario Model'!B16 -> 52507.008 | C6: ='Scenario Model'!C16 -> 77681.139 | D6: ='Scenario Model'!D16 -> -5365.2009 | E6: ='Scenario Model'!E16 -> -41696.366
A7: EBITDA Margin | B7: ='Scenario Model'!B17 -> 0.11373425 | C7: ='Scenario Model'!C17 -> 0.15672656 | D7: ='Scenario Model'!D17 -> -0.014396729 | E7: ='Scenario Model'!E17 -> -0.13047175
A8: EBIT (₹ cr) | B8: ='Scenario Model'!B21 -> 28785.888 | C8: ='Scenario Model'!C21 -> 53960.019 | D8: ='Scenario Model'!D21 -> -28621.201 | E8: ='Scenario Model'!E21 -> -64487.246
A9: Net Profit / PAT (₹ cr) | B9: ='Scenario Model'!B26 -> 17792.602 | C9: ='Scenario Model'!C26 -> 36673.2 | D9: ='Scenario Model'!D26 -> -34558.606 | E9: ='Scenario Model'!E26 -> -71362.136
A10: Net Margin | B10: ='Scenario Model'!B27 -> 0.038540154 | C10: ='Scenario Model'!C27 -> 0.073990478 | D10: ='Scenario Model'!D27 -> -0.092732946 | E10: ='Scenario Model'!E27 -> -0.22329867
A11: Interest Coverage Ratio | B11: ='Scenario Model'!B28 -> 5.6861923 | C11: ='Scenario Model'!C28 -> 10.65894 | D11: ='Scenario Model'!D28 -> -4.8204899 | E11: ='Scenario Model'!E28 -> -9.3801131
A12: Free Cash Flow (₹ cr) | B12: ='Scenario Model'!B33 -> 1569.6217 | C12: ='Scenario Model'!C33 -> 18548.12 | D12: ='Scenario Model'!D33 -> -45540.406 | E12: ='Scenario Model'!E33 -> -77102.756
A13: Net Debt / EBITDA | B13: ='Scenario Model'!B34 -> 1.1902983 | C13: ='Scenario Model'!C34 -> 0.80455824 | D13: ='Scenario Model'!D34 -> -11.648958 | E13: ='Scenario Model'!E34 -> -1.4989076
